qt1d_ideal/__init__.py
qt1d_ideal/cli.py
qt1d_ideal/core/__init__.py
qt1d_ideal/core/initial_conditions.py
qt1d_ideal/core/solver.py
qt1d_ideal/io/__init__.py
qt1d_ideal/io/config_manager.py
qt1d_ideal/io/data_handler.py
qt1d_ideal/utils/__init__.py
qt1d_ideal/utils/logger.py
qt1d_ideal/utils/timer.py
qt1d_ideal/visualization/__init__.py
qt1d_ideal/visualization/animator.py
1d_qt_ideal_solver-0.0.10.dist-info/LICENSE
1d_qt_ideal_solver-0.0.10.dist-info/METADATA
1d_qt_ideal_solver-0.0.10.dist-info/WHEEL
1d_qt_ideal_solver-0.0.10.dist-info/entry_points.txt
1d_qt_ideal_solver-0.0.10.dist-info/RECORD
