Metadata-Version: 2.3
Name: 1d-qt-ideal-solver
Version: 0.0.10
Summary: Idealized 1D quantum tunneling solver
License: MIT
Author: Sandy H. S. Herho
Author-email: sandy.herho@email.ucr.edu
Requires-Python: >=3.8,<4.0
Classifier: License :: OSI Approved :: MIT License
Classifier: Programming Language :: Python :: 3
Classifier: Programming Language :: Python :: 3.8
Classifier: Programming Language :: Python :: 3.9
Classifier: Programming Language :: Python :: 3.10
Classifier: Programming Language :: Python :: 3.11
Classifier: Programming Language :: Python :: 3.12
Classifier: Programming Language :: Python :: 3.13
Requires-Dist: matplotlib (>=3.3.0)
Requires-Dist: netCDF4 (>=1.5.0)
Requires-Dist: numba (>=0.53.0)
Requires-Dist: numpy (>=1.20.0)
Requires-Dist: scipy (>=1.7.0)
Requires-Dist: tqdm (>=4.60.0)
